spacetrace/__init__.py
spacetrace/_shaders.py
spacetrace/main.py
spacetrace/scene.py
spacetrace-0.2.1.dist-info/METADATA
spacetrace-0.2.1.dist-info/WHEEL
spacetrace-0.2.1.dist-info/licenses/LICENSE
spacetrace-0.2.1.dist-info/RECORD
