Metadata-Version: 2.4
Name: spacetrace
Version: 0.2.1
Summary: A minimalist packadge for vizualizing 3D trajectories in space.
Project-URL: Homepage, https://github.com/bionick7/space-trace
Author-email: Nick Felten <nickfelten@yahoo.com>
License: MIT License
License-File: LICENSE
Classifier: License :: OSI Approved :: MIT License
Classifier: Operating System :: OS Independent
Classifier: Programming Language :: Python :: 3
Classifier: Topic :: Scientific/Engineering :: Visualization
Requires-Python: >=3.10
Requires-Dist: numpy
Requires-Dist: raylib>=5.5.0
